LICENSE
MANIFEST.in
README.md
setup.py
docs/gen_ref_pages.py
docs/getting_started/__init__.py
qcsys/VERSION.txt
qcsys/__init__.py
qcsys.egg-info/PKG-INFO
qcsys.egg-info/SOURCES.txt
qcsys.egg-info/dependency_links.txt
qcsys.egg-info/requires.txt
qcsys.egg-info/top_level.txt
qcsys/common/__init__.py
qcsys/common/utils.py
qcsys/devices/__init__.py
qcsys/devices/ats.py
qcsys/devices/base.py
qcsys/devices/drive.py
qcsys/devices/fluxonium.py
qcsys/devices/ideal_qubit.py
qcsys/devices/kno.py
qcsys/devices/resonator.py
qcsys/devices/squid_transmon.py
qcsys/devices/system.py
qcsys/devices/transmon.py
qcsys/devices/transmon_single_charge_basis.py
qcsys/devices/truncated_transmon.py
qcsys/devices/tunable_transmon.py