Metadata-Version: 2.1
Name: qcsys
Version: 0.1.1
Summary: qcsys
Home-page: https://github.com/EQuS/qcsys
Author: Shantanu Jha, Shoumik Chowdhury
Author-email: shantanu.rajesh.jha@gmail.com
License: Apache 2.0
Project-URL: Documentation, https://equs.github.io/qcsys
Project-URL: Source Code, https://github.com/EQuS/qcsys
Project-URL: Tutorials, https://github.com/EQuS/qcsys/tree/master/tutorials
Keywords: quantum computing circuits
Classifier: Environment :: Console
Classifier: License :: OSI Approved :: Apache Software License
Classifier: Intended Audience :: Developers
Classifier: Intended Audience :: Science/Research
Classifier: Operating System :: Microsoft :: Windows
Classifier: Operating System :: MacOS :: MacOS X
Classifier: Operating System :: POSIX :: Linux
Classifier: Programming Language :: Python :: 3 :: Only
Classifier: Topic :: Scientific/Engineering
Requires-Python: >=3.7
License-File: LICENSE
Requires-Dist: numpy
Requires-Dist: matplotlib
Requires-Dist: qutip
Requires-Dist: jax[cpu]
Requires-Dist: flax
Provides-Extra: dev
Requires-Dist: jupyterlab>=3.1.0; extra == "dev"
Requires-Dist: mypy; extra == "dev"
Requires-Dist: pylint; extra == "dev"
Requires-Dist: black; extra == "dev"
Provides-Extra: docs
Requires-Dist: mkdocs; extra == "docs"
Requires-Dist: mkdocs-material; extra == "docs"
Requires-Dist: mkdocs-literate-nav; extra == "docs"
Requires-Dist: mkdocs-section-index; extra == "docs"
Requires-Dist: mkdocs-gen-files; extra == "docs"
Requires-Dist: mkdocstrings-python; extra == "docs"
